logga/VERSION
logga/__init__.py
logga/py.typed
logga/config/log.conf
logga-1.0.5.dist-info/LICENSE.md
logga-1.0.5.dist-info/METADATA
logga-1.0.5.dist-info/WHEEL
logga-1.0.5.dist-info/top_level.txt
logga-1.0.5.dist-info/RECORD
