Metadata-Version: 2.1
Name: logga
Version: 1.0.5
Summary: Python logging made super easy!
Home-page: https://github.com/loum/logga
Author: Lou Markovski
Author-email: lou.markovski@gmail.com
License: MIT
Classifier: Development Status :: 5 - Production/Stable
Classifier: Environment :: Console
Classifier: Environment :: MacOS X
Classifier: Intended Audience :: Developers
Classifier: Topic :: Software Development :: Build Tools
Classifier: License :: OSI Approved :: MIT License
Classifier: Natural Language :: English
Classifier: Operating System :: POSIX :: Linux
Classifier: Operating System :: MacOS :: MacOS X
Classifier: Programming Language :: Python :: 3
Requires-Python: >=3
License-File: LICENSE.md
Provides-Extra: dev
Requires-Dist: mkdocstrings-python ; extra == 'dev'
Requires-Dist: pytest ; extra == 'dev'
Requires-Dist: pytest-cov ; extra == 'dev'
Requires-Dist: pytest-sugar ; extra == 'dev'
Requires-Dist: sphinx-rtd-theme ; extra == 'dev'
Requires-Dist: twine ; extra == 'dev'
Requires-Dist: Sphinx ; extra == 'dev'
